<?xml version = '1.0' encoding = 'UTF-8'?>
<relationalModel class="oracle.dbtools.crest.model.design.relational.RelationalDesign" name="HR" id="97DAF9D9-A938-2E8B-CC94-2D383F309AB5" mainViewID="0E15BF67-C96A-00EF-1A98-951555191AA6">
<createdBy>PC</createdBy>
<createdTime>2024-11-08 02:10:33 UTC</createdTime>
<ownerDesignName>studentdb</ownerDesignName>
<shouldBeOpen>false</shouldBeOpen>
<selectedRDBMSSite>01F6E6D1-21D0-CFBD-ABDD-3988D1813575</selectedRDBMSSite>
<importConnectionStamps>
<importConnectionStamp class="oracle.dbtools.crest.imports.DBConnectionStamp">
<connName>로컬-HR</connName>
<connUser>HR</connUser>
<connType>1</connType>
</importConnectionStamp>
</importConnectionStamps>
</relationalModel>